Workbook

Sheet Clean Data
A1: Month | B1: Month Num | C1: Transaction Number | D1: Product Code | E1: Product Description | F1: Store Cost | G1: Sale Price | H1: Profit | I1: Commission 10% | J1: Sales Person | K1: Sale Location
A2: Jan | B2: 1 | C2: 1001 | D2: 9822 | E2: Pool Cover | F2: 58.3 | G2: 98.4 | H2: =G2-F2 -> 40.1 | I2: =H2*0.1 -> 4.01 | J2: Charlie Barns | K2: NM
A3: Jan | B3: 1 | C3: 1002 | D3: 2877 | E3: Net | F3: 11.4 | G3: 16.3 | H3: =G3-F3 -> 4.9 | I3: =H3*0.1 -> 0.49 | J3: Juan Hernandez | K3: CA
A4: Jan | B4: 1 | C4: 1003 | D4: 2499 | E4: 8 ft Hose | F4: 6.2 | G4: 9.2 | H4: =G4-F4 -> 3 | I4: =H4*0.1 -> 0.3 | J4: Doug Smith | K4: AZ
A5: Jan | B5: 1 | C5: 1004 | D5: 8722 | E5: Water Pump | F5: 344 | G5: 502 | H5: =G5-F5 -> 158 | I5: =H5*0.1 -> 15.8 | J5: Charlie Barns | K5: AZ
A6: Jan | B6: 1 | C6: 1005 | D6: 1109 | E6: Chlorine Test Kit | F6: 3 | G6: 8 | H6: =G6-F6 -> 5 | I6: =H6*0.1 -> 0.5 | J6: Doug Smith | K6: AZ
A7: Jan | B7: 1 | C7: 1006 | D7: 9822 | E7: Pool Cover | F7: 58.3 | G7: 98.4 | H7: =G7-F7 -> 40.1 | I7: =H7*0.1 -> 4.01 | J7: Doug Smith | K7: AZ
A8: Jan | B8: 1 | C8: 1007 | D8: 1109 | E8: Chlorine Test Kit | F8: 3 | G8: 8 | H8: =G8-F8 -> 5 | I8: =H8*0.1 -> 0.5 | J8: Helen Johnson | K8: NM
A9: Jan | B9: 1 | C9: 1008 | D9: 2877 | E9: Net | F9: 11.4 | G9: 16.3 | H9: =G9-F9 -> 4.9 | I9: =H9*0.1 -> 0.49 | J9: Doug Smith | K9: NM
A10: Jan | B10: 1 | C10: 1009 | D10: 1109 | E10: Chlorine Test Kit | F10: 3 | G10: 8 | H10: =G10-F10 -> 5 | I10: =H10*0.1 -> 0.5 | J10: Doug Smith | K10: AZ
A11: Jan | B11: 1 | C11: 1010 | D11: 2877 | E11: Net | F11: 11.4 | G11: 16.3 | H11: =G11-F11 -> 4.9 | I11: =H11*0.1 -> 0.49 | J11: Juan Hernandez | K11: CO
A12: Jan | B12: 1 | C12: 1011 | D12: 2877 | E12: Net | F12: 11.4 | G12: 16.3 | H12: =G12-F12 -> 4.9 | I12: =H12*0.1 -> 0.49 | J12: Juan Hernandez | K12: AZ
A13: Jan | B13: 1 | C13: 1012 | D13: 4421 | E13: Skimmer | F13: 45 | G13: 87 | H13: =G13-F13 -> 42 | I13: =H13*0.1 -> 4.2 | J13: Doug Smith | K13: NM
... A172: Dec | B172: 12 | C172: 1171 | D172: 4421 | E172: Skimmer | F172: 45 | G172: 87 | H172: =G172-F172 -> 42 | I172: =H172*0.1 -> 4.2 | J172: Juan Hernandez | K172: NV

Sheet Pivot - Monthly
B2: Monthly Sales Summary
B4: Month | C4: Transactions | D4: Total Revenue | E4: Total Cost | F4: Total Profit | G4: Total Commission | H4: Avg Sale Price | I4: Profit Margin %
B5: Jan | C5: =COUNTIF('Clean Data'!$A$2:$A$172,B5) -> 16 | D5: =SUMIF('Clean Data'!$A$2:$A$172,B5,'Clean Data'!$G$2:$G$172) -> 1418.7 | E5: =SUMIF('Clean Data'!$A$2:$A$172,B5,'Clean Data'!$F$2:$F$172) -> 932 | F5: =SUMIF('Clean Data'!$A$2:$A$172,B5,'Clean Data'!$H$2:$H$172) -> 486.7 | G5: =SUMIF('Clean Data'!$A$2:$A$172,B5,'Clean Data'!$I$2:$I$172) -> 48.67 | H5: =IFERROR(D5/C5,0) -> 88.66875 | I5: =IFERROR(F5/D5,0) -> 0.34306055
B6: Feb | C6: =COUNTIF('Clean Data'!$A$2:$A$172,B6) -> 18 | D6: =SUMIF('Clean Data'!$A$2:$A$172,B6,'Clean Data'!$G$2:$G$172) -> 971.2 | E6: =SUMIF('Clean Data'!$A$2:$A$172,B6,'Clean Data'!$F$2:$F$172) -> 605.5 | F6: =SUMIF('Clean Data'!$A$2:$A$172,B6,'Clean Data'!$H$2:$H$172) -> 365.7 | G6: =SUMIF('Clean Data'!$A$2:$A$172,B6,'Clean Data'!$I$2:$I$172) -> 36.57 | H6: =IFERROR(D6/C6,0) -> 53.955556 | I6: =IFERROR(F6/D6,0) -> 0.37654448
B7: Mar | C7: =COUNTIF('Clean Data'!$A$2:$A$172,B7) -> 14 | D7: =SUMIF('Clean Data'!$A$2:$A$172,B7,'Clean Data'!$G$2:$G$172) -> 1875.4 | E7: =SUMIF('Clean Data'!$A$2:$A$172,B7,'Clean Data'!$F$2:$F$172) -> 1235.6 | F7: =SUMIF('Clean Data'!$A$2:$A$172,B7,'Clean Data'!$H$2:$H$172) -> 639.8 | G7: =SUMIF('Clean Data'!$A$2:$A$172,B7,'Clean Data'!$I$2:$I$172) -> 63.98 | H7: =IFERROR(D7/C7,0) -> 133.95714 | I7: =IFERROR(F7/D7,0) -> 0.34115389
B8: Apr | C8: =COUNTIF('Clean Data'!$A$2:$A$172,B8) -> 12 | D8: =SUMIF('Clean Data'!$A$2:$A$172,B8,'Clean Data'!$G$2:$G$172) -> 510.7 | E8: =SUMIF('Clean Data'!$A$2:$A$172,B8,'Clean Data'!$F$2:$F$172) -> 269.8 | F8: =SUMIF('Clean Data'!$A$2:$A$172,B8,'Clean Data'!$H$2:$H$172) -> 240.9 | G8: =SUMIF('Clean Data'!$A$2:$A$172,B8,'Clean Data'!$I$2:$I$172) -> 24.09 | H8: =IFERROR(D8/C8,0) -> 42.558333 | I8: =IFERROR(F8/D8,0) -> 0.4717055
B9: May | C9: =COUNTIF('Clean Data'!$A$2:$A$172,B9) -> 18 | D9: =SUMIF('Clean Data'!$A$2:$A$172,B9,'Clean Data'!$G$2:$G$172) -> 347.4 | E9: =SUMIF('Clean Data'!$A$2:$A$172,B9,'Clean Data'!$F$2:$F$172) -> 200.7 | F9: =SUMIF('Clean Data'!$A$2:$A$172,B9,'Clean Data'!$H$2:$H$172) -> 146.7 | G9: =SUMIF('Clean Data'!$A$2:$A$172,B9,'Clean Data'!$I$2:$I$172) -> 14.67 | H9: =IFERROR(D9/C9,0) -> 19.3 | I9: =IFERROR(F9/D9,0) -> 0.42227979
B10: Jun | C10: =COUNTIF('Clean Data'!$A$2:$A$172,B10) -> 20 | D10: =SUMIF('Clean Data'!$A$2:$A$172,B10,'Clean Data'!$G$2:$G$172) -> 409.5 | E10: =SUMIF('Clean Data'!$A$2:$A$172,B10,'Clean Data'!$F$2:$F$172) -> 245.9 | F10: =SUMIF('Clean Data'!$A$2:$A$172,B10,'Clean Data'!$H$2:$H$172) -> 163.6 | G10: =SUMIF('Clean Data'!$A$2:$A$172,B10,'Clean Data'!$I$2:$I$172) -> 16.36 | H10: =IFERROR(D10/C10,0) -> 20.475 | I10: =IFERROR(F10/D10,0) -> 0.3995116
B11: Jul | C11: =COUNTIF('Clean Data'!$A$2:$A$172,B11) -> 26 | D11: =SUMIF('Clean Data'!$A$2:$A$172,B11,'Clean Data'!$G$2:$G$172) -> 3992.3 | E11: =SUMIF('Clean Data'!$A$2:$A$172,B11,'Clean Data'!$F$2:$F$172) -> 2526.1 | F11: =SUMIF('Clean Data'!$A$2:$A$172,B11,'Clean Data'!$H$2:$H$172) -> 1466.2 | G11: =SUMIF('Clean Data'!$A$2:$A$172,B11,'Clean Data'!$I$2:$I$172) -> 146.62 | H11: =IFERROR(D11/C11,0) -> 153.55 | I11: =IFERROR(F11/D11,0) -> 0.36725697
B12: Aug | C12: =COUNTIF('Clean Data'!$A$2:$A$172,B12) -> 17 | D12: =SUMIF('Clean Data'!$A$2:$A$172,B12,'Clean Data'!$G$2:$G$172) -> 2513.6 | E12: =SUMIF('Clean Data'!$A$2:$A$172,B12,'Clean Data'!$F$2:$F$172) -> 1578.2 | F12: =SUMIF('Clean Data'!$A$2:$A$172,B12,'Clean Data'!$H$2:$H$172) -> 935.4 | G12: =SUMIF('Clean Data'!$A$2:$A$172,B12,'Clean Data'!$I$2:$I$172) -> 93.54 | H12: =IFERROR(D12/C12,0) -> 147.85882 | I12: =IFERROR(F12/D12,0) -> 0.37213558
B13: Sep | C13: =COUNTIF('Clean Data'!$A$2:$A$172,B13) -> 8 | D13: =SUMIF('Clean Data'!$A$2:$A$172,B13,'Clean Data'!$G$2:$G$172) -> 1542.8 | E13: =SUMIF('Clean Data'!$A$2:$A$172,B13,'Clean Data'!$F$2:$F$172) -> 973.6 | F13: =SUMIF('Clean Data'!$A$2:$A$172,B13,'Clean Data'!$H$2:$H$172) -> 569.2 | G13: =SUMIF('Clean Data'!$A$2:$A$172,B13,'Clean Data'!$I$2:$I$172) -> 56.92 | H13: =IFERROR(D13/C13,0) -> 192.85 | I13: =IFERROR(F13/D13,0) -> 0.36893959
B14: Oct | C14: =COUNTIF('Clean Data'!$A$2:$A$172,B14) -> 8 | D14: =SUMIF('Clean Data'!$A$2:$A$172,B14,'Clean Data'!$G$2:$G$172) -> 1153.4 | E14: =SUMIF('Clean Data'!$A$2:$A$172,B14,'Clean Data'!$F$2:$F$172) -> 676.3 | F14: =SUMIF('Clean Data'!$A$2:$A$172,B14,'Clean Data'!$H$2:$H$172) -> 477.1 | G14: =SUMIF('Clean Data'!$A$2:$A$172,B14,'Clean Data'!$I$2:$I$172) -> 47.71 | H14: =IFERROR(D14/C14,0) -> 144.175 | I14: =IFERROR(F14/D14,0) -> 0.41364661
B15: Nov | C15: =COUNTIF('Clean Data'!$A$2:$A$172,B15) -> 9 | D15: =SUMIF('Clean Data'!$A$2:$A$172,B15,'Clean Data'!$G$2:$G$172) -> 1477.2 | E15: =SUMIF('Clean Data'!$A$2:$A$172,B15,'Clean Data'!$F$2:$F$172) -> 957.9 | F15: =SUMIF('Clean Data'!$A$2:$A$172,B15,'Clean Data'!$H$2:$H$172) -> 519.3 | G15: =SUMIF('Clean Data'!$A$2:$A$172,B15,'Clean Data'!$I$2:$I$172) -> 51.93 | H15: =IFERROR(D15/C15,0) -> 164.13333 | I15: =IFERROR(F15/D15,0) -> 0.35154346
B16: Dec | C16: =COUNTIF('Clean Data'!$A$2:$A$172,B16) -> 5 | D16: =SUMIF('Clean Data'!$A$2:$A$172,B16,'Clean Data'!$G$2:$G$172) -> 898.4 | E16: =SUMIF('Clean Data'!$A$2:$A$172,B16,'Clean Data'!$F$2:$F$172) -> 552.3 | F16: =SUMIF('Clean Data'!$A$2:$A$172,B16,'Clean Data'!$H$2:$H$172) -> 346.1 | G16: =SUMIF('Clean Data'!$A$2:$A$172,B16,'Clean Data'!$I$2:$I$172) -> 34.61 | H16: =IFERROR(D16/C16,0) -> 179.68 | I16: =IFERROR(F16/D16,0) -> 0.38524043
B17: TOTAL | C17: =SUM(C5:C16) -> 171 | D17: =SUM(D5:D16) -> 17110.6 | E17: =SUM(E5:E16) -> 10753.9 | F17: =SUM(F5:F16) -> 6356.7 | G17: =SUM(G5:G16) -> 635.67 | H17: =IFERROR(D17/C17,0) -> 100.06199 | I17: =IFERROR(F17/D17,0) -> 0.37150655

Sheet Pivot - Product
B2: Product Performance Summary
B4: Product | C4: Units Sold | D4: Total Revenue | E4: Total Profit | F4: Avg Profit / Unit | G4: Profit Margin % | H4: % of Total Revenue
B5: Water Pump | C5: =COUNTIF('Clean Data'!$E$2:$E$172,B5) -> 20 | D5: =SUMIF('Clean Data'!$E$2:$E$172,B5,'Clean Data'!$G$2:$G$172) -> 10040 | E5: =SUMIF('Clean Data'!$E$2:$E$172,B5,'Clean Data'!$H$2:$H$172) -> 3160 | F5: =IFERROR(E5/C5,0) -> 158 | G5: =IFERROR(E5/D5,0) -> 0.31474104 | H5: =IFERROR(D5/'Pivot - Monthly'!$D$17,0) -> 0.58677077
B6: Pool Cover | C6: =COUNTIF('Clean Data'!$E$2:$E$172,B6) -> 21 | D6: =SUMIF('Clean Data'!$E$2:$E$172,B6,'Clean Data'!$G$2:$G$172) -> 2066.4 | E6: =SUMIF('Clean Data'!$E$2:$E$172,B6,'Clean Data'!$H$2:$H$172) -> 842.1 | F6: =IFERROR(E6/C6,0) -> 40.1 | G6: =IFERROR(E6/D6,0) -> 0.40752033 | H6: =IFERROR(D6/'Pivot - Monthly'!$D$17,0) -> 0.12076724
B7: AutoVac | C7: =COUNTIF('Clean Data'!$E$2:$E$172,B7) -> 16 | D7: =SUMIF('Clean Data'!$E$2:$E$172,B7,'Clean Data'!$G$2:$G$172) -> 1984 | E7: =SUMIF('Clean Data'!$E$2:$E$172,B7,'Clean Data'!$H$2:$H$172) -> 1024 | F7: =IFERROR(E7/C7,0) -> 64 | G7: =IFERROR(E7/D7,0) -> 0.51612903 | H7: =IFERROR(D7/'Pivot - Monthly'!$D$17,0) -> 0.11595152
B8: Skimmer | C8: =COUNTIF('Clean Data'!$E$2:$E$172,B8) -> 15 | D8: =SUMIF('Clean Data'!$E$2:$E$172,B8,'Clean Data'!$G$2:$G$172) -> 1305 | E8: =SUMIF('Clean Data'!$E$2:$E$172,B8,'Clean Data'!$H$2:$H$172) -> 630 | F8: =IFERROR(E8/C8,0) -> 42 | G8: =IFERROR(E8/D8,0) -> 0.48275862 | H8: =IFERROR(D8/'Pivot - Monthly'!$D$17,0) -> 0.076268512
B9: 5 Gal Chlorine | C9: =COUNTIF('Clean Data'!$E$2:$E$172,B9) -> 9 | D9: =SUMIF('Clean Data'!$E$2:$E$172,B9,'Clean Data'!$G$2:$G$172) -> 693 | E9: =SUMIF('Clean Data'!$E$2:$E$172,B9,'Clean Data'!$H$2:$H$172) -> 315 | F9: =IFERROR(E9/C9,0) -> 35 | G9: =IFERROR(E9/D9,0) -> 0.45454545 | H9: =IFERROR(D9/'Pivot - Monthly'!$D$17,0) -> 0.04050121
B10: Net | C10: =COUNTIF('Clean Data'!$E$2:$E$172,B10) -> 24 | D10: =SUMIF('Clean Data'!$E$2:$E$172,B10,'Clean Data'!$G$2:$G$172) -> 391.2 | E10: =SUMIF('Clean Data'!$E$2:$E$172,B10,'Clean Data'!$H$2:$H$172) -> 117.6 | F10: =IFERROR(E10/C10,0) -> 4.9 | G10: =IFERROR(E10/D10,0) -> 0.3006135 | H10: =IFERROR(D10/'Pivot - Monthly'!$D$17,0) -> 0.022863021
B11: Algae Killer 8 oz | C11: =COUNTIF('Clean Data'!$E$2:$E$172,B11) -> 15 | D11: =SUMIF('Clean Data'!$E$2:$E$172,B11,'Clean Data'!$G$2:$G$172) -> 210 | E11: =SUMIF('Clean Data'!$E$2:$E$172,B11,'Clean Data'!$H$2:$H$172) -> 75 | F11: =IFERROR(E11/C11,0) -> 5 | G11: =IFERROR(E11/D11,0) -> 0.35714286 | H11: =IFERROR(D11/'Pivot - Monthly'!$D$17,0) -> 0.012273094
B12: 8 ft Hose | C12: =COUNTIF('Clean Data'!$E$2:$E$172,B12) -> 20 | D12: =SUMIF('Clean Data'!$E$2:$E$172,B12,'Clean Data'!$G$2:$G$172) -> 184 | E12: =SUMIF('Clean Data'!$E$2:$E$172,B12,'Clean Data'!$H$2:$H$172) -> 60 | F12: =IFERROR(E12/C12,0) -> 3 | G12: =IFERROR(E12/D12,0) -> 0.32608696 | H12: =IFERROR(D12/'Pivot - Monthly'!$D$17,0) -> 0.010753568
B13: Chlorine Test Kit | C13: =COUNTIF('Clean Data'!$E$2:$E$172,B13) -> 20 | D13: =SUMIF('Clean Data'!$E$2:$E$172,B13,'Clean Data'!$G$2:$G$172) -> 160 | E13: =SUMIF('Clean Data'!$E$2:$E$172,B13,'Clean Data'!$H$2:$H$172) -> 100 | F13: =IFERROR(E13/C13,0) -> 5 | G13: =IFERROR(E13/D13,0) -> 0.625 | H13: =IFERROR(D13/'Pivot - Monthly'!$D$17,0) -> 0.0093509287
B14: 1 Gal Muratic Acid | C14: =COUNTIF('Clean Data'!$E$2:$E$172,B14) -> 11 | D14: =SUMIF('Clean Data'!$E$2:$E$172,B14,'Clean Data'!$G$2:$G$172) -> 77 | E14: =SUMIF('Clean Data'!$E$2:$E$172,B14,'Clean Data'!$H$2:$H$172) -> 33 | F14: =IFERROR(E14/C14,0) -> 3 | G14: =IFERROR(E14/D14,0) -> 0.42857143 | H14: =IFERROR(D14/'Pivot - Monthly'!$D$17,0) -> 0.0045001344
B15: TOTAL | C15: =SUM(C5:C14) -> 171 | D15: =SUM(D5:D14) -> 17110.6 | E15: =SUM(E5:E14) -> 6356.7 | H15: =SUM(H5:H14) -> 1

Sheet Pivot - Sales Person
B2: Sales Person Performance
B4: Sales Person | C4: Transactions | D4: Total Revenue | E4: Total Profit | F4: Total Commission | G4: Avg Sale Price
B5: Charlie Barns | C5: =COUNTIF('Clean Data'!$J$2:$J$172,B5) -> 33 | D5: =SUMIF('Clean Data'!$J$2:$J$172,B5,'Clean Data'!$G$2:$G$172) -> 6003.5 | E5: =SUMIF('Clean Data'!$J$2:$J$172,B5,'Clean Data'!$H$2:$H$172) -> 2015.1 | F5: =SUMIF('Clean Data'!$J$2:$J$172,B5,'Clean Data'!$I$2:$I$172) -> 201.51 | G5: =IFERROR(D5/C5,0) -> 181.92424
B6: Doug Smith | C6: =COUNTIF('Clean Data'!$J$2:$J$172,B6) -> 66 | D6: =SUMIF('Clean Data'!$J$2:$J$172,B6,'Clean Data'!$G$2:$G$172) -> 5661.1 | E6: =SUMIF('Clean Data'!$J$2:$J$172,B6,'Clean Data'!$H$2:$H$172) -> 2235.9 | F6: =SUMIF('Clean Data'!$J$2:$J$172,B6,'Clean Data'!$I$2:$I$172) -> 223.59 | G6: =IFERROR(D6/C6,0) -> 85.774242
B7: Helen Johnson | C7: =COUNTIF('Clean Data'!$J$2:$J$172,B7) -> 31 | D7: =SUMIF('Clean Data'!$J$2:$J$172,B7,'Clean Data'!$G$2:$G$172) -> 3035.3 | E7: =SUMIF('Clean Data'!$J$2:$J$172,B7,'Clean Data'!$H$2:$H$172) -> 1084.1 | F7: =SUMIF('Clean Data'!$J$2:$J$172,B7,'Clean Data'!$I$2:$I$172) -> 108.41 | G7: =IFERROR(D7/C7,0) -> 97.912903
B8: Juan Hernandez | C8: =COUNTIF('Clean Data'!$J$2:$J$172,B8) -> 41 | D8: =SUMIF('Clean Data'!$J$2:$J$172,B8,'Clean Data'!$G$2:$G$172) -> 2410.7 | E8: =SUMIF('Clean Data'!$J$2:$J$172,B8,'Clean Data'!$H$2:$H$172) -> 1021.6 | F8: =SUMIF('Clean Data'!$J$2:$J$172,B8,'Clean Data'!$I$2:$I$172) -> 102.16 | G8: =IFERROR(D8/C8,0) -> 58.797561
B9: TOTAL | C9: =SUM(C5:C8) -> 171 | D9: =SUM(D5:D8) -> 17110.6 | E9: =SUM(E5:E8) -> 6356.7 | F9: =SUM(F5:F8) -> 635.67

Sheet Pivot - Location
B2: Sales by Location (State)
B4: Location | C4: Transactions | D4: Total Revenue | E4: Total Profit | F4: Avg Sale Price
B5: AZ | C5: =COUNTIF('Clean Data'!$K$2:$K$172,B5) -> 50 | D5: =SUMIF('Clean Data'!$K$2:$K$172,B5,'Clean Data'!$G$2:$G$172) -> 5660 | E5: =SUMIF('Clean Data'!$K$2:$K$172,B5,'Clean Data'!$H$2:$H$172) -> 1979.1 | F5: =IFERROR(D5/C5,0) -> 113.2
B6: NV | C6: =COUNTIF('Clean Data'!$K$2:$K$172,B6) -> 38 | D6: =SUMIF('Clean Data'!$K$2:$K$172,B6,'Clean Data'!$G$2:$G$172) -> 4722.5 | E6: =SUMIF('Clean Data'!$K$2:$K$172,B6,'Clean Data'!$H$2:$H$172) -> 1710.1 | F6: =IFERROR(D6/C6,0) -> 124.27632
B7: CA | C7: =COUNTIF('Clean Data'!$K$2:$K$172,B7) -> 46 | D7: =SUMIF('Clean Data'!$K$2:$K$172,B7,'Clean Data'!$G$2:$G$172) -> 3537.6 | E7: =SUMIF('Clean Data'!$K$2:$K$172,B7,'Clean Data'!$H$2:$H$172) -> 1485.1 | F7: =IFERROR(D7/C7,0) -> 76.904348
B8: NM | C8: =COUNTIF('Clean Data'!$K$2:$K$172,B8) -> 20 | D8: =SUMIF('Clean Data'!$K$2:$K$172,B8,'Clean Data'!$G$2:$G$172) -> 1776.9 | E8: =SUMIF('Clean Data'!$K$2:$K$172,B8,'Clean Data'!$H$2:$H$172) -> 681.8 | F8: =IFERROR(D8/C8,0) -> 88.845
B9: UT | C9: =COUNTIF('Clean Data'!$K$2:$K$172,B9) -> 11 | D9: =SUMIF('Clean Data'!$K$2:$K$172,B9,'Clean Data'!$G$2:$G$172) -> 1347.6 | E9: =SUMIF('Clean Data'!$K$2:$K$172,B9,'Clean Data'!$H$2:$H$172) -> 476.8 | F9: =IFERROR(D9/C9,0) -> 122.50909
B10: CO | C10: =COUNTIF('Clean Data'!$K$2:$K$172,B10) -> 6 | D10: =SUMIF('Clean Data'!$K$2:$K$172,B10,'Clean Data'!$G$2:$G$172) -> 66 | E10: =SUMIF('Clean Data'!$K$2:$K$172,B10,'Clean Data'!$H$2:$H$172) -> 23.8 | F10: =IFERROR(D10/C10,0) -> 11
B11: TOTAL | C11: =SUM(C5:C10) -> 171 | D11: =SUM(D5:D10) -> 17110.6 | E11: =SUM(E5:E10) -> 6356.7

Sheet Dashboard
B2: Crystal Pools — Annual Sales Dashboard
B3: Jan – Dec | Data cleaned & summarized from 171 transactions
B5: Total Revenue | E5: Total Profit | H5: Total Transactions | K5: Overall Profit Margin | N5: Avg Sale Price | Q5: Top Product
B6: ='Pivot - Monthly'!D17 -> 17110.6 | E6: ='Pivot - Monthly'!F17 -> 6356.7 | H6: ='Pivot - Monthly'!C17 -> 171 | K6: ='Pivot - Monthly'!I17 -> 0.37150655 | N6: ='Pivot - Monthly'!D17/'Pivot - Monthly'!C17 -> 100.06199 | Q6: ='Pivot - Product'!B5 -> Water Pump
B9: Top Sales Person | F9: Top Location | J9: Next-Month Revenue Forecast
B10: ='Pivot - Sales Person'!B5 -> Charlie Barns | F10: ='Pivot - Location'!B5 -> AZ | J10: =Forecast!E18 -> 1630.8515

Sheet Forecast
B2: Revenue Forecast — Next 3 Months (Linear Trend)
B3: Trend line fitted with SLOPE/INTERCEPT on the 12 months of actual revenue. Seasonality note in Word report.
B5: Month Index | C5: Month | D5: Actual Revenue | E5: Trend Line
B6: 1 | C6: Jan | D6: ='Pivot - Monthly'!D5 -> 1418.7 | E6: =SLOPE('Pivot - Monthly'!$D$5:$D$16,$B$6:$B$17)*B6+INTERCEPT('Pivot - Monthly'!$D$5:$D$16,$B$6:$B$17) -> 1252.4487
B7: 2 | C7: Feb | D7: ='Pivot - Monthly'!D6 -> 971.2 | E7: =SLOPE('Pivot - Monthly'!$D$5:$D$16,$B$6:$B$17)*B7+INTERCEPT('Pivot - Monthly'!$D$5:$D$16,$B$6:$B$17) -> 1283.9823
B8: 3 | C8: Mar | D8: ='Pivot - Monthly'!D7 -> 1875.4 | E8: =SLOPE('Pivot - Monthly'!$D$5:$D$16,$B$6:$B$17)*B8+INTERCEPT('Pivot - Monthly'!$D$5:$D$16,$B$6:$B$17) -> 1315.5159
B9: 4 | C9: Apr | D9: ='Pivot - Monthly'!D8 -> 510.7 | E9: =SLOPE('Pivot - Monthly'!$D$5:$D$16,$B$6:$B$17)*B9+INTERCEPT('Pivot - Monthly'!$D$5:$D$16,$B$6:$B$17) -> 1347.0494
B10: 5 | C10: May | D10: ='Pivot - Monthly'!D9 -> 347.4 | E10: =SLOPE('Pivot - Monthly'!$D$5:$D$16,$B$6:$B$17)*B10+INTERCEPT('Pivot - Monthly'!$D$5:$D$16,$B$6:$B$17) -> 1378.583
B11: 6 | C11: Jun | D11: ='Pivot - Monthly'!D10 -> 409.5 | E11: =SLOPE('Pivot - Monthly'!$D$5:$D$16,$B$6:$B$17)*B11+INTERCEPT('Pivot - Monthly'!$D$5:$D$16,$B$6:$B$17) -> 1410.1166
B12: 7 | C12: Jul | D12: ='Pivot - Monthly'!D11 -> 3992.3 | E12: =SLOPE('Pivot - Monthly'!$D$5:$D$16,$B$6:$B$17)*B12+INTERCEPT('Pivot - Monthly'!$D$5:$D$16,$B$6:$B$17) -> 1441.6501
B13: 8 | C13: Aug | D13: ='Pivot - Monthly'!D12 -> 2513.6 | E13: =SLOPE('Pivot - Monthly'!$D$5:$D$16,$B$6:$B$17)*B13+INTERCEPT('Pivot - Monthly'!$D$5:$D$16,$B$6:$B$17) -> 1473.1837
B14: 9 | C14: Sep | D14: ='Pivot - Monthly'!D13 -> 1542.8 | E14: =SLOPE('Pivot - Monthly'!$D$5:$D$16,$B$6:$B$17)*B14+INTERCEPT('Pivot - Monthly'!$D$5:$D$16,$B$6:$B$17) -> 1504.7172
B15: 10 | C15: Oct | D15: ='Pivot - Monthly'!D14 -> 1153.4 | E15: =SLOPE('Pivot - Monthly'!$D$5:$D$16,$B$6:$B$17)*B15+INTERCEPT('Pivot - Monthly'!$D$5:$D$16,$B$6:$B$17) -> 1536.2508
B16: 11 | C16: Nov | D16: ='Pivot - Monthly'!D15 -> 1477.2 | E16: =SLOPE('Pivot - Monthly'!$D$5:$D$16,$B$6:$B$17)*B16+INTERCEPT('Pivot - Monthly'!$D$5:$D$16,$B$6:$B$17) -> 1567.7844
B17: 12 | C17: Dec | D17: ='Pivot - Monthly'!D16 -> 898.4 | E17: =SLOPE('Pivot - Monthly'!$D$5:$D$16,$B$6:$B$17)*B17+INTERCEPT('Pivot - Monthly'!$D$5:$D$16,$B$6:$B$17) -> 1599.3179
B18: 13 | C18: Jan (Yr 2) | E18: =SLOPE('Pivot - Monthly'!$D$5:$D$16,$B$6:$B$17)*B18+INTERCEPT('Pivot - Monthly'!$D$5:$D$16,$B$6:$B$17) -> 1630.8515
B19: 14 | C19: Feb (Yr 2) | E19: =SLOPE('Pivot - Monthly'!$D$5:$D$16,$B$6:$B$17)*B19+INTERCEPT('Pivot - Monthly'!$D$5:$D$16,$B$6:$B$17) -> 1662.3851
B20: 15 | C20: Mar (Yr 2) | E20: =SLOPE('Pivot - Monthly'!$D$5:$D$16,$B$6:$B$17)*B20+INTERCEPT('Pivot - Monthly'!$D$5:$D$16,$B$6:$B$17) -> 1693.9186
B22: Projected 3-month total: | E22: =SUM(E18:E20) -> 4987.1552
B24: R-squared (fit quality): | E24: =RSQ('Pivot - Monthly'!$D$5:$D$16,$B$6:$B$17) -> 0.012278256 | F24: Low R2 reflects strong month-to-month seasonality - see moving-average alternative below and Word report for discussion.
B26: Alternative forecast: trailing 3-month moving average
B27: Basis (last 3 actual months: Oct, Nov, Dec): | E27: =AVERAGE(D15:D17) -> 1176.3333
B28: Suggested next-month forecast (moving avg): | E28: =E27 -> 1176.3333

Sheet Cleaning Log
B2: Crystal Pools — Data Cleaning Log
B3: Documents every change made between the raw file and the Clean Data sheet
B5: Issue Found | C5: Correction Applied | D5: Rows Affected
B6: Sales Person spelling | C6: 'Chalie Barns' -> 'Charlie Barns', 'Hellen Johnson' -> 'Helen Johnson' | D6: 64
B7: Product Description spelling | C7: 'Algea Killer 8 oz' -> 'Algae Killer 8 oz' | D7: 15
B8: Month name standardization | C8: 'April'->'Apr', 'June'->'Jun', 'July'->'Jul', 'Sept'->'Sep' | D8: 66
B9: Duplicate transaction numbers | C9: Checked Transaction Number for duplicates | D9: 0
B10: Missing Profit values | C10: Column was entirely blank; rebuilt as formula = Sale Price - Store Cost | D10: 171
B11: Missing Commission values | C11: Column was entirely blank; rebuilt as formula = Profit * 10% | D11: 171
B13: Total rows in dataset: 171 (no rows removed — all issues were correctable in place)
